[{"id": 1, "first_name": "Adelheid", "last_name": "Tures", "email": "atures0@fotki.com", "gender": "Male"}, {"id": 2, "first_name": "Gerick", "last_name": "Frossell", "email": "gfrossell1@house.gov", "gender": "Female"}, {"id": 3, "first_name": "Gav", "last_name": "Illyes", "email": "gillyes2@opera.com", "gender": "Male"}, {"id": 4, "first_name": "Emmi", "last_name": "Happs", "email": "ehapps3@paginegialle.it", "gender": "Male"}, {"id": 5, "first_name": "Arlyn", "last_name": "Kunzler", "email": "akunzler4@abc.net.au", "gender": "NA"}, {"id": 6, "first_name": "Meggy", "last_name": "McGready", "email": "mmcgready5@cargocollective.com", "gender": "Male"}, {"id": 7, "first_name": "Brett", "last_name": "Bottomley", "email": "bbottomley6@state.tx.us", "gender": "Female"}, {"id": 8, "first_name": "Tami", "last_name": "Stair", "email": "tstair7@wikipedia.org", "gender": "Female"}, {"id": 9, "first_name": "Cthrine", "last_name": "Padrick", "email": "cpadrick8@opera.com", "gender": "Female"}, {"id": 10, "first_name": "Rosina", "last_name": "Byatt", "email": "rbyatt9@intel.com", "gender": "Male"}, {"id": 11, "first_name": "Darryl", "last_name": "Waine", "email": "dwainea@sourceforge.net", "gender": "Female"}, {"id": 12, "first_name": "Silvanus", "last_name": "Annes", "email": "sannesb@aboutads.info", "gender": "Female"}, {"id": 13, "first_name": "Saloma", "last_name": "Coney", "email": "sconeyc@hud.gov", "gender": "Male"}, {"id": 14, "first_name": "Shurlocke", "last_name": "Bartosinski", "email": "sbartosinskid@cbsnews.com", "gender": "NA"}, {"id": 15, "first_name": "Katheryn", "last_name": "Hyslop", "email": "khyslope@abc.net.au", "gender": "Male"}, {"id": 16, "first_name": "Amory", "last_name": "Brand-Hardy", "email": "abrandhardyf@artisteer.com", "gender": "Female"}, {"id": 17, "first_name": "Luce", "last_name": "Haborn", "email": "lhaborng@fda.gov", "gender": "Genderqueer"}, {"id": 18, "first_name": "Roley", "last_name": "Whitticks", "email": "rwhitticksh@alibaba.com", "gender": "Male"}, {"id": 19, "first_name": "Sofie", "last_name": "Jirak", "email": "sjiraki@loc.gov", "gender": "Male"}, {"id": 20, "first_name": "Tracy", "last_name": "Scoffins", "email": "tscoffinsj@about.me", "gender": "Female"}, {"id": 22, "first_name": "Ed", "last_name": "Sheeran", "email": "sheeraned@gmail.com", "gender": "Male"}]